{"Nodes":[],"ExecutionTime":"2021-08-13T00:22:50.5736111Z","GenerationTime":"0001-01-01T00:00:00","PluginUserSpecFlowId":"f76ce526-9ee5-424b-ac56-8f76445dffc7","CLIUserSpecFlowId":null,"ExecutionResults":[{"ContextType":"Scenario","FeatureFolderPath":"Features","FeatureTitle":"CadastroSite","ScenarioTitle":"Cadastro de um novo usuario","ScenarioArguments":["\"teste.automacao000001@hotmail.com\""],"Status":"TestError","StepResults":[{"Duration":"00:00:15.7345539","Status":"OK","Error":null,"Outputs":null},{"Duration":"00:00:17.8467662","Status":"OK","Error":null,"Outputs":null},{"Duration":"00:00:06.8462402","Status":"OK","Error":null,"Outputs":null},{"Duration":"00:00:00.1825149","Status":"TestError","Error":"  Página My Account não encontrada\r\n  Expected string length 10 but was 762. Strings differ at index 0.\r\n  Expected: \"My Account\"\r\n  But was:  \"Robert Duncan\\r\\nSign out\\r\\nContact us\\r\\nCall us now: 0123-456-78...\"\r\n  -----------^\r\n","Outputs":null}],"Outputs":null}],"StepReports":null}